sllurp/__init__.py
sllurp/__main__.py
sllurp/cli.py
sllurp/decode.py
sllurp/llrp.py
sllurp/llrp_decoder.py
sllurp/llrp_errors.py
sllurp/llrp_proto.py
sllurp/lock.py
sllurp/log.py
sllurp/util.py
sllurp/version.py
sllurp/epc/__init__.py
sllurp/epc/gtin.py
sllurp/epc/sgtin_96.py
sllurp/verb/__init__.py
sllurp/verb/access.py
sllurp/verb/inventory.py
sllurp/verb/log.py
sllurp/verb/reset.py
sllurp-2.0.1.dist-info/LICENSE.txt
sllurp-2.0.1.dist-info/METADATA
sllurp-2.0.1.dist-info/WHEEL
sllurp-2.0.1.dist-info/entry_points.txt
sllurp-2.0.1.dist-info/top_level.txt
sllurp-2.0.1.dist-info/RECORD
